taixuanshifa/__init__.py
taixuanshifa/taixuanashifa.py
taixuanshifa/taixuandict.p
taixuanshifa/taixuandict.py
taixuanshifa/taixuanshifa.py
taixuanshifa/data/taixuandict.p
taixuanshifa-1.0.8.dist-info/METADATA
taixuanshifa-1.0.8.dist-info/WHEEL
taixuanshifa-1.0.8.dist-info/top_level.txt
taixuanshifa-1.0.8.dist-info/RECORD
