Metadata-Version: 2.1
Name: taixuanshifa
Version: 1.0.8
Summary: An alternative Iching divination tool name Tai Xuan created by a Chinese Confucian Yang Xiong (BC53 - 18CE) from Xi Han Dynasty.
Home-page: https://github.com/kentang2017/taixuanshifa
Author: Ken Tang
Author-email: kinyeah@gmail.com
License: UNKNOWN
Platform: UNKNOWN
Classifier: Programming Language :: Python :: 3
Classifier: License :: OSI Approved :: MIT License
Classifier: Operating System :: OS Independent
